examples/__init__.py
examples/config_ov.xml
examples/rda_test.py
examples/to_debug.py
examples/basics/__init__.py
examples/basics/generate_send.py
examples/basics/receive_graz.py
examples/basics/stimulate_send.py
examples/basics/stimulation_config_1.xml
examples/basics/stimulation_config_2.xml
examples/basics/stimulation_config_3.xml
examples/motor-imagery-simple/0_get-raw.py
examples/motor-imagery-simple/1_data-acquisition.py
examples/motor-imagery-simple/2_train-lda.py
examples/motor-imagery-simple/3_online-mi.py
examples/motor-imagery-simple/__init__.py
examples/tests/RDAtoLSL.py
examples/tests/__init__.py
examples/tests/exampleMarkerBasedEpoching_test_3.py
examples/tests/my_test.py
examples/tests/my_test_realtime.py
examples/tests/simpleDSP_feedback.py
examples/tests/test_alpha_comparison.py
examples/tests/testproc.py
neuxus/__init__.py
neuxus/__main__.py
neuxus/chunks.py
neuxus/keepref.py
neuxus/main.py
neuxus/node.py
neuxus/pipeline.py
neuxus/registry.py
neuxus/nodes/__init__.py
neuxus/nodes/classify.py
neuxus/nodes/display.py
neuxus/nodes/epoch_function.py
neuxus/nodes/epoching.py
neuxus/nodes/feature.py
neuxus/nodes/filter.py
neuxus/nodes/function.py
neuxus/nodes/generate.py
neuxus/nodes/io.py
neuxus/nodes/log.py
neuxus/nodes/processing.py
neuxus/nodes/read.py
neuxus/nodes/select.py
neuxus/nodes/stimulator.py
neuxus/nodes/store.py
neuxus-0.0.3.dist-info/LICENSE
neuxus-0.0.3.dist-info/METADATA
neuxus-0.0.3.dist-info/WHEEL
neuxus-0.0.3.dist-info/entry_points.txt
neuxus-0.0.3.dist-info/top_level.txt
neuxus-0.0.3.dist-info/RECORD
